lightningrobot_adapter_onebot/__init__.py
lightningrobot_adapter_onebot/core.py
lightningrobot_adapter_onebot/utils/logger.py
lightningrobot_adapter_onebot/utils/send_message.py
lightningrobot_adapter_onebot-0.1.1.dist-info/METADATA
lightningrobot_adapter_onebot-0.1.1.dist-info/WHEEL
lightningrobot_adapter_onebot-0.1.1.dist-info/RECORD
